ansie/__init__.py
ansie/misc.py
ansie/screen.py
ansie/styles.py
ansie-0.0.2.dist-info/LICENSE.txt
ansie-0.0.2.dist-info/WHEEL
ansie-0.0.2.dist-info/METADATA
ansie-0.0.2.dist-info/RECORD
